zneitiz/__init__.py
zneitiz/_enums.py
zneitiz/_exceptions.py
zneitiz/client.py
zneitiz/image.py
zneitiz/route.py
zneitiz-0.3.1.dist-info/LICENSE
zneitiz-0.3.1.dist-info/METADATA
zneitiz-0.3.1.dist-info/WHEEL
zneitiz-0.3.1.dist-info/top_level.txt
zneitiz-0.3.1.dist-info/RECORD
