Metadata-Version: 2.2
Name: zneitiz
Version: 0.3.1
Summary: A Python wrapper for the zNeitiz API
Home-page: https://github.com/z03h/zNeitiz-Client
Author: z03h
License: Mozilla Public License Version 2.0
Requires-Python: >=3.9.0
License-File: LICENSE
Requires-Dist: aiohttp<4.0
Dynamic: home-page
Dynamic: requires-python
